Workbook

Sheet region sale
A3: Row Labels | B3: Sum of Total Sales | C3: Sum of Profit
A4: (blank)
A5: West | B5: 359520.38 | C5: 331831.93
A6: South | B6: 485969.6 | C6: 453490.29
A7: North | B7: 623245.33 | C7: 580978.07
A8: East | B8: 417595.84 | C8: 389717.22
A9: Grand Total | B9: 1886331.1 | C9: 1756017.5

Sheet Product Performance
A3: Row Labels | B3: Sum of Unit Price ($) | C3: Sum of Total Sales | D3: Sum of Profit
A4: Antivirus Suite (1yr) | B4: 1079.82 | C4: 16257.29 | D4: 15177.47
A5: Bookshelf | B5: 2985 | C5: 37810 | D5: 34825
A6: Cable Management Kit | B6: 279.86 | C6: 4677.66 | D6: 4397.8
A7: Cloud Backup (1yr) | B7: 2178 | C7: 37620 | D7: 35442
A8: Design Suite License | B8: 5681 | C8: 93886 | D8: 88205
A9: Desk Lamp | B9: 599.85 | C9: 8757.81 | D9: 8157.96
A10: Ergonomic Chair | B10: 5382 | C10: 81029 | D10: 75647
A11: Filing Cabinet | B11: 3380 | C11: 54756 | D11: 51376
A12: Laptop Pro 13 | B12: 23976 | C12: 308691 | D12: 284715
A13: Laptop Pro 15 | B13: 23382 | C13: 311760 | D13: 288378
A14: Laptop Stand | B14: 1259.79 | C14: 19796.7 | D14: 18536.91
A15: Mechanical Keyboard | B15: 2069.77 | C15: 35906.01 | D15: 33836.24
... A28: Wireless Mouse | B28: 1019.66 | C28: 15744.75 | D28: 14725.09
A29: (blank)
A30: Grand Total | B30: 130313.64 | C30: 1886331.1 | D30: 1756017.5

Sheet Sheet10
A1: Sales Performance Dashboard
I3: Total Profit | M3: Total Orders | Q3: Average Discount
F6: S

Sheet Region VS Category
A3: Sum of Total Sales | B3: Column Labels
A4: Row Labels | B4: Accessories | C4: Electronics | D4: Furniture | E4: Software | F4: TOTALS | G4: (blank) | H4: Grand Total
A5: East | B5: 19696.46 | C5: 251926.57 | D5: 101491.45 | E5: 44481.36 | H5: 417595.84
A6: North | B6: 48171.7 | C6: 349477.51 | D6: 159406.49 | E6: 66189.63 | H6: 623245.33
A7: South | B7: 34213.63 | C7: 275212.08 | D7: 112713.33 | E7: 63830.56 | H7: 485969.6
A8: West | B8: 22065.8 | C8: 230644.31 | D8: 79910.54 | E8: 26899.73 | H8: 359520.38
A9: (blank)
A10: Grand Total | B10: 124147.59 | C10: 1107260.5 | D10: 453521.81 | E10: 201401.28 | H10: 1886331.1

Sheet Discount analysis
A3: Row Labels | B3: Average of Discount Amount | C3: Sum of Net Revenue ($) | D3: Sum of Discount Amount
A4: Accessories | B4: -784.01587 | C4: 116616.82 | D4: -108978.21
A5: Electronics | B5: -6461.4918 | C5: 1035695.4 | D5: -956300.78
A6: Furniture | B6: -3389.3635 | C6: 423925.02 | D6: -393166.17
A7: Software | B7: -1814.9257 | C7: 188569.4 | D7: -176047.79
A8: TOTALS | C8: 1764806.6
A9: (blank)
A10: Grand Total | B10: -3268.9859 | C10: 3529613.2 | D10: -1634493

Sheet Profit margin analysis 
A3: Row Labels | B3: Average of Profit Margin%
A4: Accessories | B4: 0.94503866
A5: Electronics | B5: 0.92056905
A6: Furniture | B6: 0.91430776
A7: Software | B7: 0.91442625
A8: TOTALS
A9: (blank)
A10: Grand Total | B10: 0.92472728

Sheet Sales Rep Performance
A3: Row Labels | B3: Sum of Revenue ($) | C3: Sum of Profit
A4: Alice Johnson | B4: 116662.99 | C4: 108104.18
A5: Bob Smith | B5: 209940.38 | C5: 197132.6
A6: Carol Lee | B6: 175764.58 | C6: 161975.73
A7: David Kim | B7: 133266.85 | C7: 123548.13
A8: Eve Torres | B8: 145432.34 | C8: 134698.59
A9: Frank Ng | B9: 226253.53 | C9: 208283.8
A10: Grace Park | B10: 195846.64 | C10: 181104.91
A11: Henry Wu | B11: 241831.26 | C11: 227741.49
A12: Iris Patel | B12: 310735.7 | C12: 291768.98
A13: James Rivera | B13: 130596.88 | C13: 121659.1
A14: (blank) | B14: 1886331.1
A15: Grand Total | B15: 3772662.3 | C15: 1756017.5

Sheet Monthly Sales Trends
A3: Row Labels | B3: Sum of Total Sales
A4: January | B4: 214761.81
A5: February | B5: 263934.02
A6: March | B6: 252722.37
A7: April | B7: 209834.32
A8: May | B8: 212708.48
A9: June | B9: 103963.65
A10: July | B10: 89627.13
A11: August | B11: 104231.25
A12: September | B12: 140666.32
A13: October | B13: 107272.21
A14: November | B14: 108247.28
A15: December | B15: 78362.31
A16: (blank)
A17: Grand Total | B17: 1886331.1

Sheet Category Performance
A3: Row Labels | B3: Sum of Revenue ($) | C3: Sum of Net Revenue ($) | D3: Sum of Profit
A4: Accessories | B4: 124147.59 | C4: 116616.82 | D4: 116508.98
A5: Electronics | B5: 1107260.5 | C5: 1035695.4 | D5: 1027865.9
A6: Furniture | B6: 453521.81 | C6: 423925.02 | D6: 422762.96
A7: Software | B7: 201401.28 | C7: 188569.4 | D7: 188879.67
A8: TOTALS | B8: 1886331.1 | C8: 1764806.6
A9: (blank)
A10: Grand Total | B10: 3772662.3 | C10: 3529613.2 | D10: 1756017.5

Sheet Sales Transactions
A1: Order ID | B1: Date | C1: Sales Rep | D1: Region | E1: Product | F1: Category | G1: Units | H1: Unit Price ($) | I1: Revenue ($) | J1: Discount (%) | K1: Net Revenue ($) | L1: Status | M1: Total Sales | N1: Profit | O1: Month | P1: Discount Amount | Q1: Profit Margin% | R1: Average Selling Price | S1: Order Size | T1: Sales Range
A2: ORD-0029 | B2: 2025-01-01 | C2: Carol Lee | D2: East | E2: Whiteboard | F2: Furniture | G2: 25 | H2: 129 | I2: =H2*G2 -> 3225 | J2: 15 | K2: =I2*(1-J2/100) -> 2741.25 | L2: Completed | M2: =G2*H2 -> 3225 | N2: =M2-H2 -> 3096 | O2: =TEXT(B2,"MMMM") -> January | P2: =H2-K2 -> -2612.25 | Q2: =N2/K2 -> 1.1294118 | R2: =K2/G2 -> 109.65 | S2: =IF(G2>=10,"Large","Small") -> Large | T2: =IF(K1>1000,"High","Low") -> High
A3: ORD-0048 | B3: 2025-01-03 | C3: Grace Park | D3: North | E3: Laptop Pro 13 | F3: Electronics | G3: 6 | H3: 999 | I3: =H3*G3 -> 5994 | J3: 10 | K3: =I3*(1-J3/100) -> 5394.6 | L3: Completed | M3: =G3*H3 -> 5994 | N3: =M3-H3 -> 4995 | O3: =TEXT(B3,"MMMM") -> January | P3: =H3-K3 -> -4395.6 | Q3: =N3/K3 -> 0.92592593 | R3: =K3/G3 -> 899.1 | S3: =IF(G3>=10,"Large","Small") -> Small | T3: =IF(K2>1000,"High","Low") -> High
A4: ORD-0153 | B4: 2025-01-03 | C4: Carol Lee | D4: East | E4: Whiteboard | F4: Furniture | G4: 3 | H4: 129 | I4: =H4*G4 -> 387 | J4: 0 | K4: =I4*(1-J4/100) -> 387 | L4: Completed | M4: =G4*H4 -> 387 | N4: =M4-H4 -> 258 | O4: =TEXT(B4,"MMMM") -> January | P4: =H4-K4 -> -258 | Q4: =N4/K4 -> 0.66666667 | R4: =K4/G4 -> 129 | S4: =IF(G4>=10,"Large","Small") -> Small | T4: =IF(K3>1000,"High","Low") -> High
A5: ORD-0037 | B5: 2025-01-08 | C5: Iris Patel | D5: North | E5: Wireless Mouse | F5: Accessories | G5: 19 | H5: 29.99 | I5: =H5*G5 -> 569.81 | J5: 5 | K5: =I5*(1-J5/100) -> 541.3195 | L5: Completed | M5: =G5*H5 -> 569.81 | N5: =M5-H5 -> 539.82 | O5: =TEXT(B5,"MMMM") -> January | P5: =H5-K5 -> -511.3295 | Q5: =N5/K5 -> 0.99722992 | R5: =K5/G5 -> 28.4905 | S5: =IF(G5>=10,"Large","Small") -> Large | T5: =IF(K4>1000,"High","Low") -> Low
A6: ORD-0258 | B6: 2025-01-08 | C6: David Kim | D6: West | E6: Cable Management Kit | F6: Accessories | G6: 20 | H6: 19.99 | I6: =H6*G6 -> 399.8 | J6: 0 | K6: =I6*(1-J6/100) -> 399.8 | L6: Completed | M6: =G6*H6 -> 399.8 | N6: =M6-H6 -> 379.81 | O6: =TEXT(B6,"MMMM") -> January | P6: =H6-K6 -> -379.81 | Q6: =N6/K6 -> 0.95 | R6: =K6/G6 -> 19.99 | S6: =IF(G6>=10,"Large","Small") -> Large | T6: =IF(K5>1000,"High","Low") -> Low
A7: ORD-0057 | B7: 2025-01-10 | C7: Eve Torres | D7: South | E7: Ergonomic Chair | F7: Furniture | G7: 11 | H7: 299 | I7: =H7*G7 -> 3289 | J7: 0 | K7: =I7*(1-J7/100) -> 3289 | L7: Completed | M7: =G7*H7 -> 3289 | N7: =M7-H7 -> 2990 | O7: =TEXT(B7,"MMMM") -> January | P7: =H7-K7 -> -2990 | Q7: =N7/K7 -> 0.90909091 | R7: =K7/G7 -> 299 | S7: =IF(G7>=10,"Large","Small") -> Large | T7: =IF(K6>1000,"High","Low") -> Low
A8: ORD-0067 | B8: 2025-01-10 | C8: Henry Wu | D8: East | E8: Whiteboard | F8: Furniture | G8: 23 | H8: 129 | I8: =H8*G8 -> 2967 | J8: 10 | K8: =I8*(1-J8/100) -> 2670.3 | L8: Completed | M8: =G8*H8 -> 2967 | N8: =M8-H8 -> 2838 | O8: =TEXT(B8,"MMMM") -> January | P8: =H8-K8 -> -2541.3 | Q8: =N8/K8 -> 1.0628019 | R8: =K8/G8 -> 116.1 | S8: =IF(G8>=10,"Large","Small") -> Large | T8: =IF(K7>1000,"High","Low") -> High
A9: ORD-0468 | B9: 2025-01-10 | C9: David Kim | D9: West | E9: Monitor 27" | F9: Electronics | G9: 23 | H9: 399 | I9: =H9*G9 -> 9177 | J9: 0 | K9: =I9*(1-J9/100) -> 9177 | L9: Completed | M9: =G9*H9 -> 9177 | N9: =M9-H9 -> 8778 | O9: =TEXT(B9,"MMMM") -> January | P9: =H9-K9 -> -8778 | Q9: =N9/K9 -> 0.95652174 | R9: =K9/G9 -> 399 | S9: =IF(G9>=10,"Large","Small") -> Large | T9: =IF(K8>1000,"High","Low") -> High
A10: ORD-0133 | B10: 2025-01-11 | C10: Eve Torres | D10: South | E10: Laptop Stand | F10: Accessories | G10: 9 | H10: 59.99 | I10: =H10*G10 -> 539.91 | J10: 5 | K10: =I10*(1-J10/100) -> 512.9145 | L10: Completed | M10: =G10*H10 -> 539.91 | N10: =M10-H10 -> 479.92 | O10: =TEXT(B10,"MMMM") -> January | P10: =H10-K10 -> -452.9245 | Q10: =N10/K10 -> 0.93567251 | R10: =K10/G10 -> 56.9905 | S10: =IF(G10>=10,"Large","Small") -> Small | T10: =IF(K9>1000,"High","Low") -> High
A11: ORD-0495 | B11: 2025-01-13 | C11: James Rivera | D11: South | E11: Laptop Stand | F11: Accessories | G11: 28 | H11: 59.99 | I11: =H11*G11 -> 1679.72 | J11: 10 | K11: =I11*(1-J11/100) -> 1511.748 | L11: Completed | M11: =G11*H11 -> 1679.72 | N11: =M11-H11 -> 1619.73 | O11: =TEXT(B11,"MMMM") -> January | P11: =H11-K11 -> -1451.758 | Q11: =N11/K11 -> 1.0714286 | R11: =K11/G11 -> 53.991 | S11: =IF(G11>=10,"Large","Small") -> Large | T11: =IF(K10>1000,"High","Low") -> Low
A12: ORD-0210 | B12: 2025-01-15 | C12: Frank Ng | D12: West | E12: Monitor 27" | F12: Electronics | G12: 26 | H12: 399 | I12: =H12*G12 -> 10374 | J12: 10 | K12: =I12*(1-J12/100) -> 9336.6 | L12: Completed | M12: =G12*H12 -> 10374 | N12: =M12-H12 -> 9975 | O12: =TEXT(B12,"MMMM") -> January | P12: =H12-K12 -> -8937.6 | Q12: =N12/K12 -> 1.0683761 | R12: =K12/G12 -> 359.1 | S12: =IF(G12>=10,"Large","Small") -> Large | T12: =IF(K11>1000,"High","Low") -> High
A13: ORD-0046 | B13: 2025-01-16 | C13: Bob Smith | D13: South | E13: Laptop Pro 13 | F13: Electronics | G13: 21 | H13: 999 | I13: =H13*G13 -> 20979 | J13: 15 | K13: =I13*(1-J13/100) -> 17832.15 | L13: Completed | M13: =G13*H13 -> 20979 | N13: =M13-H13 -> 19980 | O13: =TEXT(B13,"MMMM") -> January | P13: =H13-K13 -> -16833.15 | Q13: =N13/K13 -> 1.1204482 | R13: =K13/G13 -> 849.15 | S13: =IF(G13>=10,"Large","Small") -> Large | T13: =IF(K12>1000,"High","Low") -> High
... A501: ORD-0321 | B501: 2026-06-12 | C501: Alice Johnson | D501: North | E501: Laptop Stand | F501: Accessories | G501: 30 | H501: 59.99 | I501: =H501*G501 -> 1799.7 | J501: 5 | K501: =I501*(1-J501/100) -> 1709.715 | L501: Completed | M501: =G501*H501 -> 1799.7 | N501: =M501-H501 -> 1739.71 | O501: =TEXT(B501,"MMMM") -> June | P501: =H501-K501 -> -1649.725 | Q501: =N501/K501 -> 1.0175439 | R501: =K501/G501 -> 56.9905 | S501: =IF(G501>=10,"Large","Small") -> Large | T501: =IF(K500>1000,"High","Low") -> High
F502: TOTALS | G502: =SUM(G2:G501) -> 7637 | I502: =SUM(I2:I501) -> 1886331.1 | K502: =SUM(K2:K501) -> 1764806.6

Sheet Summary by Rep
A1: Sales Rep | B1: Region | C1: Orders | D1: Total Revenue ($) | E1: Net Revenue ($) | F1: Avg Order Value ($)
A2: Alice Johnson | B2: North | C2: =COUNTIF('Sales Transactions'!C:C,A2) -> 40 | D2: =SUMIF('Sales Transactions'!C:C,A2,'Sales Transactions'!I:I) -> 116662.99 | E2: =SUMIF('Sales Transactions'!C:C,A2,'Sales Transactions'!K:K) -> 108899.52 | F2: =IFERROR(D2/C2,0) -> 2916.5748
A3: Bob Smith | B3: South | C3: =COUNTIF('Sales Transactions'!C:C,A3) -> 44 | D3: =SUMIF('Sales Transactions'!C:C,A3,'Sales Transactions'!I:I) -> 209940.38 | E3: =SUMIF('Sales Transactions'!C:C,A3,'Sales Transactions'!K:K) -> 196296.11 | F3: =IFERROR(D3/C3,0) -> 4771.3723
A4: Carol Lee | B4: East | C4: =COUNTIF('Sales Transactions'!C:C,A4) -> 46 | D4: =SUMIF('Sales Transactions'!C:C,A4,'Sales Transactions'!I:I) -> 175764.58 | E4: =SUMIF('Sales Transactions'!C:C,A4,'Sales Transactions'!K:K) -> 166358.87 | F4: =IFERROR(D4/C4,0) -> 3820.9691
A5: David Kim | B5: West | C5: =COUNTIF('Sales Transactions'!C:C,A5) -> 49 | D5: =SUMIF('Sales Transactions'!C:C,A5,'Sales Transactions'!I:I) -> 133266.85 | E5: =SUMIF('Sales Transactions'!C:C,A5,'Sales Transactions'!K:K) -> 126716.3 | F5: =IFERROR(D5/C5,0) -> 2719.7316
A6: Eve Torres | B6: South | C6: =COUNTIF('Sales Transactions'!C:C,A6) -> 51 | D6: =SUMIF('Sales Transactions'!C:C,A6,'Sales Transactions'!I:I) -> 145432.34 | E6: =SUMIF('Sales Transactions'!C:C,A6,'Sales Transactions'!K:K) -> 137243.16 | F6: =IFERROR(D6/C6,0) -> 2851.6145
A7: Frank Ng | B7: West | C7: =COUNTIF('Sales Transactions'!C:C,A7) -> 57 | D7: =SUMIF('Sales Transactions'!C:C,A7,'Sales Transactions'!I:I) -> 226253.53 | E7: =SUMIF('Sales Transactions'!C:C,A7,'Sales Transactions'!K:K) -> 211272.06 | F7: =IFERROR(D7/C7,0) -> 3969.3602
A8: Grace Park | B8: North | C8: =COUNTIF('Sales Transactions'!C:C,A8) -> 55 | D8: =SUMIF('Sales Transactions'!C:C,A8,'Sales Transactions'!I:I) -> 195846.64 | E8: =SUMIF('Sales Transactions'!C:C,A8,'Sales Transactions'!K:K) -> 181769.83 | F8: =IFERROR(D8/C8,0) -> 3560.848
A9: Henry Wu | B9: East | C9: =COUNTIF('Sales Transactions'!C:C,A9) -> 53 | D9: =SUMIF('Sales Transactions'!C:C,A9,'Sales Transactions'!I:I) -> 241831.26 | E9: =SUMIF('Sales Transactions'!C:C,A9,'Sales Transactions'!K:K) -> 225304.93 | F9: =IFERROR(D9/C9,0) -> 4562.854
A10: Iris Patel | B10: North | C10: =COUNTIF('Sales Transactions'!C:C,A10) -> 61 | D10: =SUMIF('Sales Transactions'!C:C,A10,'Sales Transactions'!I:I) -> 310735.7 | E10: =SUMIF('Sales Transactions'!C:C,A10,'Sales Transactions'!K:K) -> 286529.74 | F10: =IFERROR(D10/C10,0) -> 5094.0279
A11: James Rivera | B11: South | C11: =COUNTIF('Sales Transactions'!C:C,A11) -> 44 | D11: =SUMIF('Sales Transactions'!C:C,A11,'Sales Transactions'!I:I) -> 130596.88 | E11: =SUMIF('Sales Transactions'!C:C,A11,'Sales Transactions'!K:K) -> 124416.07 | F11: =IFERROR(D11/C11,0) -> 2968.1109
A12: TOTAL | C12: =SUM(C2:C11) -> 500 | D12: =SUM(D2:D11) -> 1886331.1 | E12: =SUM(E2:E11) -> 1764806.6

Sheet Summary by Category
A1: Category | B1: Orders | C1: Total Revenue ($) | D1: Net Revenue ($) | E1: % of Net Revenue
A2: Electronics | B2: =COUNTIF('Sales Transactions'!F:F,A2) -> 148 | C2: =SUMIF('Sales Transactions'!F:F,A2,'Sales Transactions'!I:I) -> 1107260.5 | D2: =SUMIF('Sales Transactions'!F:F,A2,'Sales Transactions'!K:K) -> 1035695.4 | E2: =IFERROR(D2/SUM(D2:D5),0) -> 0.58686054
A3: Accessories | B3: =COUNTIF('Sales Transactions'!F:F,A3) -> 139 | C3: =SUMIF('Sales Transactions'!F:F,A3,'Sales Transactions'!I:I) -> 124147.59 | D3: =SUMIF('Sales Transactions'!F:F,A3,'Sales Transactions'!K:K) -> 116616.82 | E3: =IFERROR(D3/SUM(D2:D5),0) -> 0.066079091
A4: Furniture | B4: =COUNTIF('Sales Transactions'!F:F,A4) -> 116 | C4: =SUMIF('Sales Transactions'!F:F,A4,'Sales Transactions'!I:I) -> 453521.81 | D4: =SUMIF('Sales Transactions'!F:F,A4,'Sales Transactions'!K:K) -> 423925.02 | E4: =IFERROR(D4/SUM(D2:D5),0) -> 0.24021047
A5: Software | B5: =COUNTIF('Sales Transactions'!F:F,A5) -> 97 | C5: =SUMIF('Sales Transactions'!F:F,A5,'Sales Transactions'!I:I) -> 201401.28 | D5: =SUMIF('Sales Transactions'!F:F,A5,'Sales Transactions'!K:K) -> 188569.4 | E5: =IFERROR(D5/SUM(D2:D5),0) -> 0.1068499
A6: TOTAL | B6: =SUM(B2:B5) -> 500 | C6: =SUM(C2:C5) -> 1886331.1 | D6: =SUM(D2:D5) -> 1764806.6

Sheet Monthly Trend
A1: Month | B1: Orders | C1: Total Revenue ($) | D1: Net Revenue ($) | E1: MoM Growth (%)
A2: Jan 2025 | B2: =COUNTIFS('Sales Transactions'!B:B,">="&DATE(2025,1,1),'Sales Transactions'!B:B,"<"&DATE(2025,2,1)) -> 0 | C2: =SUMIFS('Sales Transactions'!I:I,'Sales Transactions'!B:B,">="&DATE(2025,1,1),'Sales Transactions'!B:B,"<"&DATE(2025,2,1)) -> 0 | D2: =SUMIFS('Sales Transactions'!K:K,'Sales Transactions'!B:B,">="&DATE(2025,1,1),'Sales Transactions'!B:B,"<"&DATE(2025,2,1)) -> 0 | E2: —
A3: Feb 2025 | B3: =COUNTIFS('Sales Transactions'!B:B,">="&DATE(2025,2,1),'Sales Transactions'!B:B,"<"&DATE(2025,3,1)) -> 0 | C3: =SUMIFS('Sales Transactions'!I:I,'Sales Transactions'!B:B,">="&DATE(2025,2,1),'Sales Transactions'!B:B,"<"&DATE(2025,3,1)) -> 0 | D3: =SUMIFS('Sales Transactions'!K:K,'Sales Transactions'!B:B,">="&DATE(2025,2,1),'Sales Transactions'!B:B,"<"&DATE(2025,3,1)) -> 0 | E3: =IFERROR((C3-C2)/C2,0) -> 0
A4: Mar 2025 | B4: =COUNTIFS('Sales Transactions'!B:B,">="&DATE(2025,3,1),'Sales Transactions'!B:B,"<"&DATE(2025,4,1)) -> 0 | C4: =SUMIFS('Sales Transactions'!I:I,'Sales Transactions'!B:B,">="&DATE(2025,3,1),'Sales Transactions'!B:B,"<"&DATE(2025,4,1)) -> 0 | D4: =SUMIFS('Sales Transactions'!K:K,'Sales Transactions'!B:B,">="&DATE(2025,3,1),'Sales Transactions'!B:B,"<"&DATE(2025,4,1)) -> 0 | E4: =IFERROR((C4-C3)/C3,0) -> 0
A5: Apr 2025 | B5: =COUNTIFS('Sales Transactions'!B:B,">="&DATE(2025,4,1),'Sales Transactions'!B:B,"<"&DATE(2025,5,1)) -> 0 | C5: =SUMIFS('Sales Transactions'!I:I,'Sales Transactions'!B:B,">="&DATE(2025,4,1),'Sales Transactions'!B:B,"<"&DATE(2025,5,1)) -> 0 | D5: =SUMIFS('Sales Transactions'!K:K,'Sales Transactions'!B:B,">="&DATE(2025,4,1),'Sales Transactions'!B:B,"<"&DATE(2025,5,1)) -> 0 | E5: =IFERROR((C5-C4)/C4,0) -> 0
A6: May 2025 | B6: =COUNTIFS('Sales Transactions'!B:B,">="&DATE(2025,5,1),'Sales Transactions'!B:B,"<"&DATE(2025,6,1)) -> 0 | C6: =SUMIFS('Sales Transactions'!I:I,'Sales Transactions'!B:B,">="&DATE(2025,5,1),'Sales Transactions'!B:B,"<"&DATE(2025,6,1)) -> 0 | D6: =SUMIFS('Sales Transactions'!K:K,'Sales Transactions'!B:B,">="&DATE(2025,5,1),'Sales Transactions'!B:B,"<"&DATE(2025,6,1)) -> 0 | E6: =IFERROR((C6-C5)/C5,0) -> 0
A7: Jun 2025 | B7: =COUNTIFS('Sales Transactions'!B:B,">="&DATE(2025,6,1),'Sales Transactions'!B:B,"<"&DATE(2025,7,1)) -> 0 | C7: =SUMIFS('Sales Transactions'!I:I,'Sales Transactions'!B:B,">="&DATE(2025,6,1),'Sales Transactions'!B:B,"<"&DATE(2025,7,1)) -> 0 | D7: =SUMIFS('Sales Transactions'!K:K,'Sales Transactions'!B:B,">="&DATE(2025,6,1),'Sales Transactions'!B:B,"<"&DATE(2025,7,1)) -> 0 | E7: =IFERROR((C7-C6)/C6,0) -> 0
A8: Jul 2025 | B8: =COUNTIFS('Sales Transactions'!B:B,">="&DATE(2025,7,1),'Sales Transactions'!B:B,"<"&DATE(2025,8,1)) -> 0 | C8: =SUMIFS('Sales Transactions'!I:I,'Sales Transactions'!B:B,">="&DATE(2025,7,1),'Sales Transactions'!B:B,"<"&DATE(2025,8,1)) -> 0 | D8: =SUMIFS('Sales Transactions'!K:K,'Sales Transactions'!B:B,">="&DATE(2025,7,1),'Sales Transactions'!B:B,"<"&DATE(2025,8,1)) -> 0 | E8: =IFERROR((C8-C7)/C7,0) -> 0
A9: Aug 2025 | B9: =COUNTIFS('Sales Transactions'!B:B,">="&DATE(2025,8,1),'Sales Transactions'!B:B,"<"&DATE(2025,9,1)) -> 0 | C9: =SUMIFS('Sales Transactions'!I:I,'Sales Transactions'!B:B,">="&DATE(2025,8,1),'Sales Transactions'!B:B,"<"&DATE(2025,9,1)) -> 0 | D9: =SUMIFS('Sales Transactions'!K:K,'Sales Transactions'!B:B,">="&DATE(2025,8,1),'Sales Transactions'!B:B,"<"&DATE(2025,9,1)) -> 0 | E9: =IFERROR((C9-C8)/C8,0) -> 0
A10: Sep 2025 | B10: =COUNTIFS('Sales Transactions'!B:B,">="&DATE(2025,9,1),'Sales Transactions'!B:B,"<"&DATE(2025,10,1)) -> 0 | C10: =SUMIFS('Sales Transactions'!I:I,'Sales Transactions'!B:B,">="&DATE(2025,9,1),'Sales Transactions'!B:B,"<"&DATE(2025,10,1)) -> 0 | D10: =SUMIFS('Sales Transactions'!K:K,'Sales Transactions'!B:B,">="&DATE(2025,9,1),'Sales Transactions'!B:B,"<"&DATE(2025,10,1)) -> 0 | E10: =IFERROR((C10-C9)/C9,0) -> 0
A11: Oct 2025 | B11: =COUNTIFS('Sales Transactions'!B:B,">="&DATE(2025,10,1),'Sales Transactions'!B:B,"<"&DATE(2025,11,1)) -> 0 | C11: =SUMIFS('Sales Transactions'!I:I,'Sales Transactions'!B:B,">="&DATE(2025,10,1),'Sales Transactions'!B:B,"<"&DATE(2025,11,1)) -> 0 | D11: =SUMIFS('Sales Transactions'!K:K,'Sales Transactions'!B:B,">="&DATE(2025,10,1),'Sales Transactions'!B:B,"<"&DATE(2025,11,1)) -> 0 | E11: =IFERROR((C11-C10)/C10,0) -> 0
A12: Nov 2025 | B12: =COUNTIFS('Sales Transactions'!B:B,">="&DATE(2025,11,1),'Sales Transactions'!B:B,"<"&DATE(2025,12,1)) -> 0 | C12: =SUMIFS('Sales Transactions'!I:I,'Sales Transactions'!B:B,">="&DATE(2025,11,1),'Sales Transactions'!B:B,"<"&DATE(2025,12,1)) -> 0 | D12: =SUMIFS('Sales Transactions'!K:K,'Sales Transactions'!B:B,">="&DATE(2025,11,1),'Sales Transactions'!B:B,"<"&DATE(2025,12,1)) -> 0 | E12: =IFERROR((C12-C11)/C11,0) -> 0
A13: Dec 2025 | B13: =COUNTIFS('Sales Transactions'!B:B,">="&DATE(2025,12,1),'Sales Transactions'!B:B,"<"&DATE(2026,1,1)) -> 0 | C13: =SUMIFS('Sales Transactions'!I:I,'Sales Transactions'!B:B,">="&DATE(2025,12,1),'Sales Transactions'!B:B,"<"&DATE(2026,1,1)) -> 0 | D13: =SUMIFS('Sales Transactions'!K:K,'Sales Transactions'!B:B,">="&DATE(2025,12,1),'Sales Transactions'!B:B,"<"&DATE(2026,1,1)) -> 0 | E13: =IFERROR((C13-C12)/C12,0) -> 0
A14: Jan 2026 | B14: =COUNTIFS('Sales Transactions'!B:B,">="&DATE(2026,1,1),'Sales Transactions'!B:B,"<"&DATE(2026,2,1)) -> 0 | C14: =SUMIFS('Sales Transactions'!I:I,'Sales Transactions'!B:B,">="&DATE(2026,1,1),'Sales Transactions'!B:B,"<"&DATE(2026,2,1)) -> 0 | D14: =SUMIFS('Sales Transactions'!K:K,'Sales Transactions'!B:B,">="&DATE(2026,1,1),'Sales Transactions'!B:B,"<"&DATE(2026,2,1)) -> 0 | E14: =IFERROR((C14-C13)/C13,0) -> 0
A15: Feb 2026 | B15: =COUNTIFS('Sales Transactions'!B:B,">="&DATE(2026,2,1),'Sales Transactions'!B:B,"<"&DATE(2026,3,1)) -> 0 | C15: =SUMIFS('Sales Transactions'!I:I,'Sales Transactions'!B:B,">="&DATE(2026,2,1),'Sales Transactions'!B:B,"<"&DATE(2026,3,1)) -> 0 | D15: =SUMIFS('Sales Transactions'!K:K,'Sales Transactions'!B:B,">="&DATE(2026,2,1),'Sales Transactions'!B:B,"<"&DATE(2026,3,1)) -> 0 | E15: =IFERROR((C15-C14)/C14,0) -> 0
A16: Mar 2026 | B16: =COUNTIFS('Sales Transactions'!B:B,">="&DATE(2026,3,1),'Sales Transactions'!B:B,"<"&DATE(2026,4,1)) -> 0 | C16: =SUMIFS('Sales Transactions'!I:I,'Sales Transactions'!B:B,">="&DATE(2026,3,1),'Sales Transactions'!B:B,"<"&DATE(2026,4,1)) -> 0 | D16: =SUMIFS('Sales Transactions'!K:K,'Sales Transactions'!B:B,">="&DATE(2026,3,1),'Sales Transactions'!B:B,"<"&DATE(2026,4,1)) -> 0 | E16: =IFERROR((C16-C15)/C15,0) -> 0
A17: Apr 2026 | B17: =COUNTIFS('Sales Transactions'!B:B,">="&DATE(2026,4,1),'Sales Transactions'!B:B,"<"&DATE(2026,5,1)) -> 0 | C17: =SUMIFS('Sales Transactions'!I:I,'Sales Transactions'!B:B,">="&DATE(2026,4,1),'Sales Transactions'!B:B,"<"&DATE(2026,5,1)) -> 0 | D17: =SUMIFS('Sales Transactions'!K:K,'Sales Transactions'!B:B,">="&DATE(2026,4,1),'Sales Transactions'!B:B,"<"&DATE(2026,5,1)) -> 0 | E17: =IFERROR((C17-C16)/C16,0) -> 0
A18: May 2026 | B18: =COUNTIFS('Sales Transactions'!B:B,">="&DATE(2026,5,1),'Sales Transactions'!B:B,"<"&DATE(2026,6,1)) -> 0 | C18: =SUMIFS('Sales Transactions'!I:I,'Sales Transactions'!B:B,">="&DATE(2026,5,1),'Sales Transactions'!B:B,"<"&DATE(2026,6,1)) -> 0 | D18: =SUMIFS('Sales Transactions'!K:K,'Sales Transactions'!B:B,">="&DATE(2026,5,1),'Sales Transactions'!B:B,"<"&DATE(2026,6,1)) -> 0 | E18: =IFERROR((C18-C17)/C17,0) -> 0
A19: Jun 2026 | B19: =COUNTIFS('Sales Transactions'!B:B,">="&DATE(2026,6,1),'Sales Transactions'!B:B,"<"&DATE(2026,7,1)) -> 0 | C19: =SUMIFS('Sales Transactions'!I:I,'Sales Transactions'!B:B,">="&DATE(2026,6,1),'Sales Transactions'!B:B,"<"&DATE(2026,7,1)) -> 0 | D19: =SUMIFS('Sales Transactions'!K:K,'Sales Transactions'!B:B,">="&DATE(2026,6,1),'Sales Transactions'!B:B,"<"&DATE(2026,7,1)) -> 0 | E19: =IFERROR((C19-C18)/C18,0) -> 0
